{
  "$schema": "http://json.schemastore.org/sarif-1.0.0",
  "version": "1.0.0",
  "runs": [
    {
      "tool": {
        "name": "Microsoft (R) Visual C# Compiler",
        "version": "5.6.0.0",
        "fileVersion": "5.6.0-2.26177.108 (cf1948f9c20bc33556719613def8cbbf05e9865f)",
        "semanticVersion": "5.6.0",
        "language": "en-US"
      },
      "results": [
        {
          "ruleId": "CS8618",
          "level": "warning",
          "message": "Non-nullable property 'FullName' must contain a non-null value when exiting constructor. Consider adding the 'required' modifier or declaring the property as nullable.",
          "locations": [
            {
              "resultFile": {
                "uri": "file:///C:/Users/310476/Main_HAP_Pod1/HealthApp/HealthApp/Model/Patient.cs",
                "region": {
                  "startLine": 32,
                  "startColumn": 16,
                  "endLine": 32,
                  "endColumn": 23
                }
              }
            }
          ],
          "relatedLocations": [
            {
              "physicalLocation": {
                "uri": "file:///C:/Users/310476/Main_HAP_Pod1/HealthApp/HealthApp/Model/Patient.cs",
                "region": {
                  "startLine": 18,
                  "startColumn": 23,
                  "endLine": 18,
                  "endColumn": 31
                }
              }
            }
          ],
          "properties": {
            "warningLevel": 1
          }
        },
        {
          "ruleId": "CS8618",
          "level": "warning",
          "message": "Non-nullable property 'Patient' must contain a non-null value when exiting constructor. Consider adding the 'required' modifier or declaring the property as nullable.",
          "locations": [
            {
              "resultFile": {
                "uri": "file:///C:/Users/310476/Main_HAP_Pod1/HealthApp/HealthApp/Model/Appointment.cs",
                "region": {
                  "startLine": 19,
                  "startColumn": 24,
                  "endLine": 19,
                  "endColumn": 31
                }
              }
            }
          ],
          "relatedLocations": [
            {
              "physicalLocation": {
                "uri": "file:///C:/Users/310476/Main_HAP_Pod1/HealthApp/HealthApp/Model/Appointment.cs",
                "region": {
                  "startLine": 19,
                  "startColumn": 24,
                  "endLine": 19,
                  "endColumn": 31
                }
              }
            }
          ],
          "properties": {
            "warningLevel": 1
          }
        },
        {
          "ruleId": "CS8618",
          "level": "warning",
          "message": "Non-nullable property 'Doctor' must contain a non-null value when exiting constructor. Consider adding the 'required' modifier or declaring the property as nullable.",
          "locations": [
            {
              "resultFile": {
                "uri": "file:///C:/Users/310476/Main_HAP_Pod1/HealthApp/HealthApp/Model/Appointment.cs",
                "region": {
                  "startLine": 21,
                  "startColumn": 23,
                  "endLine": 21,
                  "endColumn": 29
                }
              }
            }
          ],
          "relatedLocations": [
            {
              "physicalLocation": {
                "uri": "file:///C:/Users/310476/Main_HAP_Pod1/HealthApp/HealthApp/Model/Appointment.cs",
                "region": {
                  "startLine": 21,
                  "startColumn": 23,
                  "endLine": 21,
                  "endColumn": 29
                }
              }
            }
          ],
          "properties": {
            "warningLevel": 1
          }
        },
        {
          "ruleId": "CS8618",
          "level": "warning",
          "message": "Non-nullable property 'TimeSlot' must contain a non-null value when exiting constructor. Consider adding the 'required' modifier or declaring the property as nullable.",
          "locations": [
            {
              "resultFile": {
                "uri": "file:///C:/Users/310476/Main_HAP_Pod1/HealthApp/HealthApp/Model/Appointment.cs",
                "region": {
                  "startLine": 25,
                  "startColumn": 23,
                  "endLine": 25,
                  "endColumn": 31
                }
              }
            }
          ],
          "relatedLocations": [
            {
              "physicalLocation": {
                "uri": "file:///C:/Users/310476/Main_HAP_Pod1/HealthApp/HealthApp/Model/Appointment.cs",
                "region": {
                  "startLine": 25,
                  "startColumn": 23,
                  "endLine": 25,
                  "endColumn": 31
                }
              }
            }
          ],
          "properties": {
            "warningLevel": 1
          }
        },
        {
          "ruleId": "CS8618",
          "level": "warning",
          "message": "Non-nullable property 'FullName' must contain a non-null value when exiting constructor. Consider adding the 'required' modifier or declaring the property as nullable.",
          "locations": [
            {
              "resultFile": {
                "uri": "file:///C:/Users/310476/Main_HAP_Pod1/HealthApp/HealthApp/Model/Doctor.cs",
                "region": {
                  "startLine": 24,
                  "startColumn": 23,
                  "endLine": 24,
                  "endColumn": 31
                }
              }
            }
          ],
          "relatedLocations": [
            {
              "physicalLocation": {
                "uri": "file:///C:/Users/310476/Main_HAP_Pod1/HealthApp/HealthApp/Model/Doctor.cs",
                "region": {
                  "startLine": 24,
                  "startColumn": 23,
                  "endLine": 24,
                  "endColumn": 31
                }
              }
            }
          ],
          "properties": {
            "warningLevel": 1
          }
        }
      ],
      "rules": {
        "CS8618": {
          "id": "CS8618",
          "shortDescription": "Non-nullable field must contain a non-null value when exiting constructor. Consider adding the 'required' modifier or declaring as nullable.",
          "defaultLevel": "warning",
          "helpUri": "https://msdn.microsoft.com/query/roslyn.query?appId=roslyn&k=k(CS8618)",
          "properties": {
            "category": "Compiler",
            "isEnabledByDefault": true,
            "tags": [
              "Compiler",
              "Telemetry"
            ]
          }
        }
      }
    }
  ]
}